all_lines.py
cli.py
code_lines.py
comment_lines.py
empty_lines.py
file_info.py
Cinfo-0.1.0.dist-info/LICENSE
Cinfo-0.1.0.dist-info/METADATA
Cinfo-0.1.0.dist-info/WHEEL
Cinfo-0.1.0.dist-info/entry_points.txt
Cinfo-0.1.0.dist-info/top_level.txt
Cinfo-0.1.0.dist-info/RECORD
