Metadata-Version: 2.1
Name: Cinfo
Version: 0.1.0
Summary: a CLI program to know about your written code for Unix ( linux / macOS ).
Home-page: https://github.com/codinggmae/Cinfo
Author-email: coding.game82@gmail.com
License: MIT
Classifier: Programming Language :: Python :: 3
Classifier: License :: OSI Approved :: MIT License
Classifier: Operating System :: POSIX :: Linux
Classifier: Operating System :: MacOS :: MacOS X
Requires-Python: >=3.11
License-File: LICENSE
Requires-Dist: click>=8.1.7
Requires-Dist: tabulate>=0.9.0
